odherogrid/__init__.py
odherogrid/cli/__init__.py
odherogrid/cli/help.py
odherogrid/cli/params.py
odherogrid/cli/parse.py
odherogrid/cli/utils.py
odherogrid/config.py
odherogrid/enums.py
odherogrid/error.py
odherogrid/herogrid.py
odherogrid/logging.py
odherogrid/odapi.py
odherogrid/odhg.py
odherogrid/resources.py
odherogrid/settings.py
odherogrid-0.3.1.dist-info/entry_points.txt
odherogrid-0.3.1.dist-info/LICENSE
odherogrid-0.3.1.dist-info/WHEEL
odherogrid-0.3.1.dist-info/METADATA
odherogrid-0.3.1.dist-info/RECORD
