Metadata-Version: 2.1
Name: odherogrid
Version: 0.3.1
Summary: Dota 2 hero grid generator using OpenDotaAPI stats
Home-page: https://github.com/PederHA/odherogrid
Author: PederHA
Author-email: peder.andresen@gmail.com
Requires-Python: >=3.7,<4.0
Classifier: Programming Language :: Python :: 3
Classifier: Programming Language :: Python :: 3.7
Classifier: Programming Language :: Python :: 3.8
Requires-Dist: click (>=7.0,<8.0)
Requires-Dist: httpx (>=0.11.1,<0.12.0)
Requires-Dist: pyyaml (>=5.2,<6.0)
Requires-Dist: terminaltables (>=3.1.0,<4.0.0)
